    Compiled from "LongLongString.java"
    class LongLongString extends java.lang.Object{
    public LongLongString();
      Code:
       0:	aload_0
       1:	invokespecial	#1; //Method java/lang/Object."<init>":()V
       4:	ldc	#2; //String This is a really long long long long long long long long long long long long long long long long long  long long long long long long long long long string for example.
       6:	astore_1
       7:	return
    
    public static void main(java.lang.String[]);
      Code:
       0:	new	#3; //class LongLongString
       3:	dup
       4:	invokespecial	#4; //Method "<init>":()V
       7:	pop
       8:	return
    
    }
